examples/__init__.py
examples/test_llms.py
examples/motto/__init__.py
examples/motto/llm_gate.py
examples/motto/utils.py
examples/motto/agents/__init__.py
examples/motto/agents/agent.py
examples/motto/agents/anthropic_agent.py
examples/motto/agents/api_importer.py
examples/motto/agents/gpt_agent.py
examples/motto/agents/messages_processor.py
examples/motto/agents/metta_agent.py
examples/motto/agents/openrouter_agent.py
examples/motto/agents/retrieval_agent.py
examples/motto/agents/data_processors/__init__.py
examples/motto/agents/data_processors/doc_processor.py
examples/motto/agents/data_processors/embedings_getters.py
examples/motto/langchain_agents/__init__.py
examples/motto/langchain_agents/langchain_agent.py
examples/motto/snet_sdk_agents/__init__.py
examples/motto/snet_sdk_agents/snet_sdk_agent.py
examples/motto/sparql_gate/__init__.py
examples/motto/sparql_gate/sparql_gate.py
examples/motto/thread_agents/__init__.py
examples/motto/thread_agents/thread_agents.py
metta_motto-0.0.11.dist-info/licenses/LICENSE
motto/__init__.py
motto/llm_gate.py
motto/utils.py
motto/agents/__init__.py
motto/agents/agent.py
motto/agents/anthropic_agent.py
motto/agents/api_importer.py
motto/agents/gpt_agent.py
motto/agents/messages_processor.py
motto/agents/metta_agent.py
motto/agents/openrouter_agent.py
motto/agents/retrieval_agent.py
motto/agents/data_processors/__init__.py
motto/agents/data_processors/doc_processor.py
motto/agents/data_processors/embedings_getters.py
motto/langchain_agents/__init__.py
motto/langchain_agents/langchain_agent.py
motto/snet_sdk_agents/__init__.py
motto/snet_sdk_agents/snet_sdk_agent.py
motto/sparql_gate/__init__.py
motto/sparql_gate/sparql_gate.py
motto/thread_agents/__init__.py
motto/thread_agents/thread_agents.py
metta_motto-0.0.11.dist-info/METADATA
metta_motto-0.0.11.dist-info/WHEEL
metta_motto-0.0.11.dist-info/top_level.txt
metta_motto-0.0.11.dist-info/RECORD
